gnosari_engine/__init__.py
gnosari_engine/cli/__init__.py
gnosari_engine/cli/commands/__init__.py
gnosari_engine/cli/commands/base_command.py
gnosari_engine/cli/commands/knowledge_command.py
gnosari_engine/cli/commands/knowledge_setup_command.py
gnosari_engine/cli/commands/learn_command.py
gnosari_engine/cli/commands/push_command.py
gnosari_engine/cli/commands/run_command.py
gnosari_engine/cli/commands/start_command.py
gnosari_engine/cli/commands/status_command.py
gnosari_engine/cli/commands/task_run_command.py
gnosari_engine/cli/commands/version_command.py
gnosari_engine/cli/commands/view_command.py
gnosari_engine/cli/commands.py
gnosari_engine/cli/event_display.py
gnosari_engine/cli/interfaces.py
gnosari_engine/cli/logger_service.py
gnosari_engine/cli/logging_config.py
gnosari_engine/cli/main.py
gnosari_engine/cli/services.py
gnosari_engine/config/.context.md
gnosari_engine/config/__init__.py
gnosari_engine/config/configuration_service.py
gnosari_engine/config/env_helpers.py
gnosari_engine/config/env_substitutor.py
gnosari_engine/config/interfaces.py
gnosari_engine/config/services.py
gnosari_engine/config/strategies.py
gnosari_engine/factories/.context.md
gnosari_engine/factories/__init__.py
gnosari_engine/factories/configuration_service_factory.py
gnosari_engine/factories/domain_factory_interface.py
gnosari_engine/factories/domain_object_factory.py
gnosari_engine/factories/interfaces.py
gnosari_engine/knowledge/__init__.py
gnosari_engine/knowledge/components.py
gnosari_engine/knowledge/events.py
gnosari_engine/knowledge/factories/__init__.py
gnosari_engine/knowledge/factories/knowledge_factory.py
gnosari_engine/knowledge/interfaces.py
gnosari_engine/knowledge/loaders/__init__.py
gnosari_engine/knowledge/loaders/file.py
gnosari_engine/knowledge/loaders/loader_factory.py
gnosari_engine/knowledge/loaders/sitemap.py
gnosari_engine/knowledge/loaders/website.py
gnosari_engine/knowledge/providers/__init__.py
gnosari_engine/knowledge/providers/opensearch.py
gnosari_engine-0.2.4.dist-info/METADATA
gnosari_engine-0.2.4.dist-info/WHEEL
gnosari_engine-0.2.4.dist-info/entry_points.txt
gnosari_engine-0.2.4.dist-info/licenses/LICENSE
gnosari_engine-0.2.4.dist-info/RECORD
