Metadata-Version: 2.4
Name: gnosari-engine
Version: 0.2.4
Summary: A powerful framework for orchestrating multi-agent teams using Large Language Models. Create intelligent AI agent swarms that collaborate through streaming delegation and dynamic tool discovery.
License-File: LICENSE
Author: daviunx
Author-email: david.marsa@neomanex.com
Requires-Python: >=3.12,<=3.14
Classifier: Programming Language :: Python :: 3
Classifier: Programming Language :: Python :: 3.12
Classifier: Programming Language :: Python :: 3.13
Classifier: Programming Language :: Python :: 3.14
Requires-Dist: PyJWT (>=2.8.0,<3.0.0)
Requires-Dist: PyYAML (>=6.0,<7.0)
Requires-Dist: aiohttp (>=3.9.0,<4.0.0)
Requires-Dist: aiosqlite (>=0.21.0,<0.22.0)
Requires-Dist: asyncpg (>=0.30.0,<0.31.0)
Requires-Dist: boto3 (>=1.35.0,<2.0.0)
Requires-Dist: celery[redis] (>=5.5.0,<6.0.0)
Requires-Dist: claude-agent-sdk (>=0.1.6,<0.2.0)
Requires-Dist: click (>=8.0.0,<9.0.0)
Requires-Dist: fastmcp (>=2.11.3,<3.0.0)
Requires-Dist: flower (>=2.0.0,<3.0.0)
Requires-Dist: greenlet (>=3.2.4,<4.0.0)
Requires-Dist: httpx (>=0.28.1,<0.29.0)
Requires-Dist: instructor (>=1.0.0,<2.0.0)
Requires-Dist: lxml (>=6.0.1,<7.0.0)
Requires-Dist: openai (>=1.100.1,<2.0.0)
Requires-Dist: openai-agents (>=0.2.10,<0.3.0)
Requires-Dist: opensearch-py (>=2.8.0,<3.0.0)
Requires-Dist: psutil (>=6.1.0,<7.0.0)
Requires-Dist: pymysql (>=1.1.0,<2.0.0)
Requires-Dist: pytest-asyncio (>=1.1.0,<2.0.0)
Requires-Dist: python-dotenv (>=1.0.0,<2.0.0)
Requires-Dist: pytube (>=15.0.0,<16.0.0)
Requires-Dist: redis (>=5.2.0,<6.0.0)
Requires-Dist: requests (>=2.31.0,<3.0.0)
Requires-Dist: requests-aws4auth (>=1.3.0,<2.0.0)
Requires-Dist: rich (>=13.0.0,<14.0.0)
Requires-Dist: sqlalchemy (>=2.0.0,<3.0.0)
Requires-Dist: tiktoken (>=0.5.0,<1.0.0)
Requires-Dist: websockets (>=15.0.1,<16.0.0)
Requires-Dist: youtube-transcript-api (>=1.2.2,<2.0.0)
